diffir/__init__.py
diffir/batchrun.py
diffir/create_landing_page.py
diffir/run.py
diffir/utils.py
diffir/measure/__init__.py
diffir/measure/qrels.py
diffir/measure/unsupervised.py
diffir/templates/landing.html
diffir/templates/template.html
diffir/weight/__init__.py
diffir/weight/custom.py
diffir/weight/unsupervised.py
diffir/weight/weights_builder.py
diffir-0.2.0.dist-info/LICENSE
diffir-0.2.0.dist-info/METADATA
diffir-0.2.0.dist-info/WHEEL
diffir-0.2.0.dist-info/entry_points.txt
diffir-0.2.0.dist-info/top_level.txt
diffir-0.2.0.dist-info/RECORD
