Metadata-Version: 2.1
Name: diffir
Version: 0.2.0
Summary: Tool for visually diffing the difference between two TREC run files.
Home-page: https://github.com/capreolus-ir/diffir
Author: Kevin Martin Jose, Thong Nguyen, Sean MacAvaney, Jeff Dalton, Andrew Yates
Author-email: diffir@googlegroups.com
License: UNKNOWN
Platform: UNKNOWN
Classifier: Programming Language :: Python :: 3
Classifier: Operating System :: OS Independent
Requires-Python: >=3.6
Requires-Dist: ir-measures (>=0.1.4)
Requires-Dist: mako (~=1.1)
Requires-Dist: ir-datasets (>=0.3.1)
Requires-Dist: pytrec-eval (>=0.5)
Requires-Dist: intervaltree (>=3.1.0)
Requires-Dist: rich (>=9.13.0)
Requires-Dist: pyahocorasick (>=1.4.1)
Requires-Dist: nltk (>=3.5)
Requires-Dist: numpy
Requires-Dist: scipy
Requires-Dist: pandas
